compass/__init__.py
compass/__main__.py
compass/exception.py
compass/number.py
compass/version.py
compass/model/__init__.py
compass/model/base.py
compass/model/factory.py
compass/pipeline/__init__.py
compass/pipeline/base.py
compass/pipeline/change.py
compass/pipeline/init.py
compass/source/__init__.py
compass/source/base.py
compass/source/factory.py
compass/source/file.py
compass/step/__init__.py
compass/step/base.py
compass/step/change.py
compass/step/init.py
compass/step/print.py
compass/step/report.py
compass/step/validate.py
compass/target/__init__.py
compass/target/base.py
compass/target/factory.py
compass/target/file.py
compass_investor-0.0.5.dist-info/LICENSE
compass_investor-0.0.5.dist-info/METADATA
compass_investor-0.0.5.dist-info/WHEEL
compass_investor-0.0.5.dist-info/entry_points.txt
compass_investor-0.0.5.dist-info/top_level.txt
compass_investor-0.0.5.dist-info/RECORD
