Metadata-Version: 2.1
Name: compass-investor
Version: 0.0.5
Summary: Leading investors to theirs targets.
Author-email: "Dinaldo A. Pessoa" <dinaldoap@gmail.com>
License: MIT License
Project-URL: repository, https://github.com/dinaldoap/compass
Classifier: Development Status :: 4 - Beta
Classifier: Programming Language :: Python :: 3
Requires-Python: >=3.8
License-File: LICENSE
Requires-Dist: pandas
Requires-Dist: openpyxl
Requires-Dist: babel
Requires-Dist: pandera
